{
  "_meta": {
    "title": "Religions du Monde",
    "emoji": "🙏",
    "source": "Pew Research 2023"
  },
  "dominantes": [
    {
      "id": "christianisme",
      "label": "Christianisme",
      "couleur": "#4080e0",
      "emoji": "✝️",
      "sous": [
        "Catholique",
        "Protestant",
        "Orthodox"
      ],
      "pays": [
        "US",
        "CA",
        "BR",
        "AR",
        "MX",
        "CO",
        "PE",
        "VE",
        "CL",
        "EC",
        "BO",
        "PY",
        "UY",
        "GB",
        "IE",
        "FR",
        "ES",
        "PT",
        "IT",
        "DE",
        "PL",
        "RO",
        "GR",
        "RU",
        "UA",
        "BY",
        "ET",
        "NG",
        "GH",
        "ZA",
        "KE",
        "TZ",
        "UG",
        "CM",
        "AO",
        "MZ",
        "PH",
        "AU",
        "NZ",
        "PG"
      ]
    },
    {
      "id": "islam",
      "label": "Islam",
      "couleur": "#20c060",
      "emoji": "☪️",
      "sous": [
        "Sunnite",
        "Chiite"
      ],
      "pays": [
        "SA",
        "AE",
        "QA",
        "KW",
        "BH",
        "OM",
        "YE",
        "IQ",
        "IR",
        "SY",
        "LB",
        "JO",
        "EG",
        "LY",
        "TN",
        "DZ",
        "MA",
        "SD",
        "SO",
        "DJ",
        "ER",
        "TR",
        "PK",
        "AF",
        "BD",
        "MY",
        "ID",
        "SN",
        "ML",
        "BF",
        "NE",
        "TD",
        "GM",
        "GN",
        "SL",
        "MR",
        "UZ",
        "KZ",
        "TM",
        "KG",
        "TJ",
        "AZ",
        "MN"
      ]
    },
    {
      "id": "hindouisme",
      "label": "Hindouisme",
      "couleur": "#e08020",
      "emoji": "🕉️",
      "pays": [
        "IN",
        "NP",
        "MU",
        "TT",
        "GY",
        "SR",
        "FJ",
        "BD",
        "LK"
      ]
    },
    {
      "id": "bouddhisme",
      "label": "Bouddhisme",
      "couleur": "#e0c020",
      "emoji": "☸️",
      "pays": [
        "TH",
        "MM",
        "KH",
        "LA",
        "BT",
        "MN",
        "LK",
        "JP",
        "VN",
        "TW",
        "CN",
        "KR",
        "SG"
      ]
    },
    {
      "id": "judaisme",
      "label": "Judaïsme",
      "couleur": "#6060c0",
      "emoji": "✡️",
      "pays": [
        "IL"
      ]
    }
  ]
}